secops_mcp/__init__.py
secops_mcp/server.py
secops_mcp/utils.py
secops_mcp/tools/__init__.py
secops_mcp/tools/data_table_management.py
secops_mcp/tools/entity_lookup.py
secops_mcp/tools/feed_management.py
secops_mcp/tools/ioc_matches.py
secops_mcp/tools/log_ingestion.py
secops_mcp/tools/parser_management.py
secops_mcp/tools/reference_list_management.py
secops_mcp/tools/search.py
secops_mcp/tools/security_alerts.py
secops_mcp/tools/security_events.py
secops_mcp/tools/security_rules.py
secops_mcp/tools/threat_intel.py
secops_mcp/tools/udm_search.py
google_secops_mcp-0.5.2.dist-info/METADATA
google_secops_mcp-0.5.2.dist-info/WHEEL
google_secops_mcp-0.5.2.dist-info/entry_points.txt
google_secops_mcp-0.5.2.dist-info/top_level.txt
google_secops_mcp-0.5.2.dist-info/RECORD
