Metadata-Version: 2.4
Name: google-secops-mcp
Version: 0.5.2
Summary: Google SecOps MCP server
Author-email: Google SecOps Team <chronicle@google.com>
Project-URL: Homepage, https://github.com/google/mcp-security
Project-URL: Documentation, https://github.com/google/mcp-security/tree/main/server/secops#readme
Project-URL: Repository, https://github.com/google/mcp-security/tree/main/server/secops
Project-URL: Issues, https://github.com/google/mcp-security/issues
Keywords: google,security,chronicle,secops,mcp
Classifier: Programming Language :: Python :: 3
Classifier: Programming Language :: Python :: 3.11
Classifier: Topic :: Security
Requires-Python: >=3.11
Requires-Dist: httpx>=0.28.1
Requires-Dist: mcp[cli]>=1.25.0
Requires-Dist: secops>=0.34.0
Requires-Dist: google-auth>=2.47.0
Requires-Dist: google-auth-httplib2>=0.3.0
Requires-Dist: google-api-python-client>=2.187.0
Provides-Extra: test
Requires-Dist: pytest>=7.0.0; extra == "test"
Requires-Dist: pytest-asyncio>=0.21.0; extra == "test"
